baidupcs_py/__init__.py
baidupcs_py/app/__init__.py
baidupcs_py/app/account.py
baidupcs_py/app/app.py
baidupcs_py/baidupcs/__init__.py
baidupcs_py/baidupcs/api.py
baidupcs_py/baidupcs/errors.py
baidupcs_py/baidupcs/inner.py
baidupcs_py/baidupcs/pcs.py
baidupcs_py/baidupcs/phone.py
baidupcs_py/commands/__init__.py
baidupcs_py/commands/cat.py
baidupcs_py/commands/cloud.py
baidupcs_py/commands/display.py
baidupcs_py/commands/download.py
baidupcs_py/commands/errors.py
baidupcs_py/commands/file_operators.py
baidupcs_py/commands/index.html
baidupcs_py/commands/list_files.py
baidupcs_py/commands/play.py
baidupcs_py/commands/search.py
baidupcs_py/commands/server.py
baidupcs_py/commands/share.py
baidupcs_py/commands/sifter.py
baidupcs_py/commands/sync.py
baidupcs_py/commands/upload.py
baidupcs_py/commands/user.py
baidupcs_py/common/concurrent.py
baidupcs_py/common/constant.py
baidupcs_py/common/crypto.py
baidupcs_py/common/downloader.py
baidupcs_py/common/io.py
baidupcs_py/common/path.py
baidupcs_py/common/progress_bar.py
baidupcs_py/utils.py
baidupcs_py-0.4.0.dist-info/entry_points.txt
baidupcs_py-0.4.0.dist-info/LICENSE
baidupcs_py-0.4.0.dist-info/WHEEL
baidupcs_py-0.4.0.dist-info/METADATA
baidupcs_py-0.4.0.dist-info/RECORD
